magic_repr/__init__.py
repr-0.3.1.dist-info/DESCRIPTION.rst
repr-0.3.1.dist-info/METADATA
repr-0.3.1.dist-info/RECORD
repr-0.3.1.dist-info/WHEEL
repr-0.3.1.dist-info/metadata.json
repr-0.3.1.dist-info/top_level.txt
